{"0xfd3fe6cf9b7fa75a1a093fe1664272271999a8c0": {"0x5150d2869ce26095f4493bce916d9c0292d5d0fe": {"ether": 0, "functions": {"1cb9ce63": {"count": 1, "sig_lookup": ["makeCall(address,bytes)"], "ether": 0}}}}, "0x99b001735036d937b4a11c17a9a44f86fbddf4d0": {"0xfd3fe6cf9b7fa75a1a093fe1664272271999a8c0": {"ether": 0, "functions": {"fae9e186": {"count": 1, "sig_lookup": [], "ether": 0}}}, "0x69b148395ce0015c13e36bffbad63f49ef874e03": {"ether": 234923777778813801, "functions": {"": {"count": 1, "sig_lookup": ["fallback"], "ether": 234923777778813801}}}}, "0x5150d2869ce26095f4493bce916d9c0292d5d0fe": {"0x99b001735036d937b4a11c17a9a44f86fbddf4d0": {"ether": 0, "functions": {"a64ed8ba": {"count": 1, "sig_lookup": ["tokensCount()"], "ether": 0}, "23b872dd": {"count": 1, "sig_lookup": ["gasprice_bit_ether(int128)", "transferFrom(address,address,uint256)"], "ether": 0}, "b4dc3dc7": {"count": 1, "sig_lookup": ["unbundle(address,uint256)"], "ether": 0}, "4f64b2be": {"count": 1, "sig_lookup": ["tokens(uint256)"], "ether": 0}}}}, "0x69b148395ce0015c13e36bffbad63f49ef874e03": {"0xb97351c9a656fbf2cca667b78678a22feaa7f262": {"ether": 0, "functions": {"70a08231": {"count": 5, "sig_lookup": ["passphrase_calculate_transfer(uint64,address)", "balanceOf(address)", "branch_passphrase_public(uint256,bytes8)"], "ether": 0}, "a9059cbb": {"count": 1, "sig_lookup": ["many_msg_babbage(bytes1)", "transfer(bytes4[9],bytes5[6],int48[11])", "transfer(address,uint256)"], "ether": 0}, "23b872dd": {"count": 1, "sig_lookup": ["gasprice_bit_ether(int128)", "transferFrom(address,address,uint256)"], "ether": 0}}}, "0x99b001735036d937b4a11c17a9a44f86fbddf4d0": {"ether": 0, "functions": {"dd62ed3e": {"count": 1, "sig_lookup": ["remove_good(uint256[],bytes8,bool)", "allowance(address,address)"], "ether": 0}}}, "0x69b148395ce0015c13e36bffbad63f49ef874e03": {"ether": 0, "functions": {"70a08231": {"count": 1, "sig_lookup": ["passphrase_calculate_transfer(uint64,address)", "balanceOf(address)", "branch_passphrase_public(uint256,bytes8)"], "ether": 0}}}, "0xed4f53268bfdff39b36e8786247ba3a02cf34b04": {"ether": 0, "functions": {"23b872dd": {"count": 1, "sig_lookup": ["gasprice_bit_ether(int128)", "transferFrom(address,address,uint256)"], "ether": 0}}}}, "0xc0829421c1d260bd3cb3e0f06cfe2d52db2ce315": {"0xb97351c9a656fbf2cca667b78678a22feaa7f262": {"ether": 0, "functions": {"70a08231": {"count": 3, "sig_lookup": ["passphrase_calculate_transfer(uint64,address)", "balanceOf(address)", "branch_passphrase_public(uint256,bytes8)"], "ether": 0}, "a9059cbb": {"count": 1, "sig_lookup": ["many_msg_babbage(bytes1)", "transfer(bytes4[9],bytes5[6],int48[11])", "transfer(address,uint256)"], "ether": 0}}}}, "0x818e6fecd516ecc3849daf6845e3ec868087b755": {"0x99b001735036d937b4a11c17a9a44f86fbddf4d0": {"ether": 0, "functions": {"cb3c28c7": {"count": 1, "sig_lookup": ["trade(address,uint256,address,address,uint256,uint256,address)"], "ether": 0}}}}, "0x91a502c678605fbce581eae053319747482276b9": {"0xb97351c9a656fbf2cca667b78678a22feaa7f262": {"ether": 0, "functions": {"088322ef": {"count": 1, "sig_lookup": ["tradeWithHint(address,address,uint256,address,address,uint256,uint256,address,bytes)"], "ether": 0}}}, "0xed4f53268bfdff39b36e8786247ba3a02cf34b04": {"ether": 234923777778813801, "functions": {"": {"count": 1, "sig_lookup": ["fallback"], "ether": 234923777778813801}}}}, "0x63825c174ab367968ec60f061753d3bbd36a0d8f": {"0x69b148395ce0015c13e36bffbad63f49ef874e03": {"ether": 0, "functions": {"7cd44272": {"count": 1, "sig_lookup": ["getConversionRate(address,address,uint256,uint256)"], "ether": 0}, "6cf69811": {"count": 1, "sig_lookup": ["trade(address,uint256,address,address,uint256,bool)"], "ether": 0}}}}, "0x798abda6cc246d0edba912092a2a3dbd3d11191b": {"0xed4f53268bfdff39b36e8786247ba3a02cf34b04": {"ether": 0, "functions": {"b8e9c22e": {"count": 1, "sig_lookup": ["getRate(address,uint256,bool,uint256)"], "ether": 0}, "c6fd2103": {"count": 1, "sig_lookup": ["recordImbalance(address,int256,uint256,uint256)"], "ether": 0}}}}, "0xdfc85c08d5e5924ab49750e006cf8a826ffb7b13": {"0xed4f53268bfdff39b36e8786247ba3a02cf34b04": {"ether": 0, "functions": {"a58092b7": {"count": 1, "sig_lookup": ["getSanityRate(address,address)"], "ether": 0}}}}, "0x6e106a75d369d09a9ea1dcc16da844792aa669a3": {"0x69b148395ce0015c13e36bffbad63f49ef874e03": {"ether": 0, "functions": {"6432679f": {"count": 1, "sig_lookup": ["getUserCapInWei(address)"], "ether": 0}}}}, "0xfce10cbf5171dc12c215bbcca5dd75cbaea72506": {"0xed4f53268bfdff39b36e8786247ba3a02cf34b04": {"ether": 0, "functions": {"70a08231": {"count": 1, "sig_lookup": ["passphrase_calculate_transfer(uint64,address)", "balanceOf(address)", "branch_passphrase_public(uint256,bytes8)"], "ether": 0}}}}, "0xed4f53268bfdff39b36e8786247ba3a02cf34b04": {"0x69b148395ce0015c13e36bffbad63f49ef874e03": {"ether": 0, "functions": {"fd062d3b": {"count": 1, "sig_lookup": ["handleFees(uint256,address,address)"], "ether": 0}}}}, "0xb97351c9a656fbf2cca667b78678a22feaa7f262": {"0x99b001735036d937b4a11c17a9a44f86fbddf4d0": {"ether": 234923777778813801, "functions": {"": {"count": 1, "sig_lookup": ["fallback"], "ether": 234923777778813801}}}}}