{"0x6ed8c6cd1ed7e412fb88c8a97a178533bbfa26db": {"0xd27797e0ed95fe57127e15b0f30651a9a8d096b8": {"ether": 0, "functions": {"c8c01a55": {"count": 1, "sig_lookup": ["request(address,uint256)"], "ether": 0}, "c77e7614": {"count": 1, "sig_lookup": ["getTotalWithdrawAmount()"], "ether": 0}, "62a5af3b": {"count": 1, "sig_lookup": ["freeze()"], "ether": 0}, "51cff8d9": {"count": 1, "sig_lookup": ["withdraw(address)"], "ether": 0}}}}, "0xd27797e0ed95fe57127e15b0f30651a9a8d096b8": {"0x6ed8c6cd1ed7e412fb88c8a97a178533bbfa26db": {"ether": 0, "functions": {"18160ddd": {"count": 1, "sig_lookup": ["totalSupply()", "voting_var(address,uint256,int128,int128)"], "ether": 0}, "70a08231": {"count": 2, "sig_lookup": ["branch_passphrase_public(uint256,bytes8)", "passphrase_calculate_transfer(uint64,address)", "balanceOf(address)"], "ether": 0}, "98d5fdca": {"count": 1, "sig_lookup": ["getPrice()"], "ether": 0}, "6e947298": {"count": 1, "sig_lookup": ["getETHBalance()"], "ether": 0}, "313ce567": {"count": 2, "sig_lookup": ["available_assert_time(uint16,uint64)", "decimals()"], "ether": 0}}}}, "0xf0ee6b27b759c9893ce4f094b49ad28fd15a23e4": {"0xd27797e0ed95fe57127e15b0f30651a9a8d096b8": {"ether": 0, "functions": {"70a08231": {"count": 2, "sig_lookup": ["branch_passphrase_public(uint256,bytes8)", "passphrase_calculate_transfer(uint64,address)", "balanceOf(address)"], "ether": 0}}}}, "0x514910771af9ca656af840dff83e8264ecf986ca": {"0xd27797e0ed95fe57127e15b0f30651a9a8d096b8": {"ether": 0, "functions": {"70a08231": {"count": 2, "sig_lookup": ["branch_passphrase_public(uint256,bytes8)", "passphrase_calculate_transfer(uint64,address)", "balanceOf(address)"], "ether": 0}}}}, "0xd26114cd6ee289accf82350c8d8487fedb8a0c07": {"0xd27797e0ed95fe57127e15b0f30651a9a8d096b8": {"ether": 0, "functions": {"70a08231": {"count": 2, "sig_lookup": ["branch_passphrase_public(uint256,bytes8)", "passphrase_calculate_transfer(uint64,address)", "balanceOf(address)"], "ether": 0}}}}, "0x263c618480dbe35c300d8d5ecda19bbb986acaed": {"0xd27797e0ed95fe57127e15b0f30651a9a8d096b8": {"ether": 0, "functions": {"70a08231": {"count": 2, "sig_lookup": ["branch_passphrase_public(uint256,bytes8)", "passphrase_calculate_transfer(uint64,address)", "balanceOf(address)"], "ether": 0}}}}}